DssPyLib/Mesh.py
DssPyLib/PlotUtils.py
DssPyLib/__init__.py
DssPyLib/Domains/Domain.py
DssPyLib/Domains/Ellipse.py
DssPyLib/Domains/Line.py
DssPyLib/Domains/Point.py
DssPyLib/Domains/Rectangle.py
DssPyLib/Domains/__init__.py
DssPyLib/Solvers/Electrostatic.py
DssPyLib/Solvers/Magnetostatic.py
DssPyLib/Solvers/Solve.py
DssPyLib/Solvers/Solver.py
DssPyLib/Solvers/__init__.py
DssPyLib-0.2.5.dist-info/LICENSE
DssPyLib-0.2.5.dist-info/METADATA
DssPyLib-0.2.5.dist-info/WHEEL
DssPyLib-0.2.5.dist-info/top_level.txt
DssPyLib-0.2.5.dist-info/RECORD
