Metadata-Version: 2.1
Name: DssPyLib
Version: 0.2.5
Summary: 2-D Finite Element Package
Home-page: https://github.com/nithingoona/dsspylib
Author: Nithin Goona
License: UNKNOWN
Keywords: fem,softwareX,Poisson equation
Platform: UNKNOWN
Requires-Python: <4,>=3.8
License-File: LICENSE
Requires-Dist: numpy (>=1.23.1)
Requires-Dist: joblib (>=1.1.0)
Requires-Dist: matplotlib (>=3.5.2)
Requires-Dist: scipy (>=1.8.1)
